optkeras/__init__.py
optkeras/optkeras.py
optkeras-0.0.7.dist-info/LICENSE
optkeras-0.0.7.dist-info/METADATA
optkeras-0.0.7.dist-info/WHEEL
optkeras-0.0.7.dist-info/top_level.txt
optkeras-0.0.7.dist-info/RECORD
