Metadata-Version: 2.1
Name: optkeras
Version: 0.0.7
Summary: OptKeras: Wrapper of Keras and Optuna to optimize hyperparameters of Deep Learning.
Home-page: https://github.com/Minyus/optkeras
Author: Yusuke Minami
Author-email: me@minyus.github.com
License: MIT
Keywords: keras optuna
Platform: UNKNOWN
Classifier: Development Status :: 3 - Alpha
Classifier: Natural Language :: English
Classifier: License :: OSI Approved :: MIT License
Classifier: Programming Language :: Python :: 3.6
Classifier: Operating System :: OS Independent
Requires-Dist: keras
Requires-Dist: optuna (>=0.9.0)
Requires-Dist: numpy
